finsight/__init__.py
finsight/indicators/__init__.py
finsight-0.1.0.dist-info/LICENSE
finsight-0.1.0.dist-info/METADATA
finsight-0.1.0.dist-info/WHEEL
finsight-0.1.0.dist-info/top_level.txt
finsight-0.1.0.dist-info/RECORD
