Metadata-Version: 2.1
Name: finsight
Version: 0.1.0
Summary: A package to provide financial insights from price data
Home-page: https://github.com/BDaws04/finsight
Author: Ben Dawson
Author-email: bjdawson1012@gmail.com
License: UNKNOWN
Platform: UNKNOWN
Classifier: Programming Language :: Python :: 3
Classifier: License :: OSI Approved :: MIT License
Classifier: Operating System :: OS Independent
Requires-Python: >=3.6
